{
  "version": 2,
  "extractor": "papercropper",
  "figures": [
    {
      "url": "assets/figures/openreview/openreview-neurips-2025-gupggcm4wh/fig-001.webp",
      "caption": "",
      "page": 0,
      "index": 1,
      "width": 1352,
      "height": 538,
      "label": "Figure"
    },
    {
      "url": "assets/figures/openreview/openreview-neurips-2025-gupggcm4wh/fig-002.webp",
      "caption": "",
      "page": 0,
      "index": 2,
      "width": 1375,
      "height": 867,
      "label": "Figure"
    },
    {
      "url": "assets/figures/openreview/openreview-neurips-2025-gupggcm4wh/fig-003.webp",
      "caption": "",
      "page": 0,
      "index": 3,
      "width": 1423,
      "height": 800,
      "label": "Figure"
    },
    {
      "url": "assets/figures/openreview/openreview-neurips-2025-gupggcm4wh/fig-004.webp",
      "caption": "",
      "page": 0,
      "index": 4,
      "width": 1438,
      "height": 488,
      "label": "Figure"
    },
    {
      "url": "assets/figures/openreview/openreview-neurips-2025-gupggcm4wh/fig-005.webp",
      "caption": "",
      "page": 0,
      "index": 5,
      "width": 709,
      "height": 546,
      "label": "Figure"
    },
    {
      "url": "assets/figures/openreview/openreview-neurips-2025-gupggcm4wh/fig-006.webp",
      "caption": "",
      "page": 0,
      "index": 6,
      "width": 1442,
      "height": 377,
      "label": "Figure"
    },
    {
      "url": "assets/figures/openreview/openreview-neurips-2025-gupggcm4wh/fig-007.webp",
      "caption": "",
      "page": 0,
      "index": 7,
      "width": 1426,
      "height": 798,
      "label": "Figure"
    },
    {
      "url": "assets/figures/openreview/openreview-neurips-2025-gupggcm4wh/fig-008.webp",
      "caption": "",
      "page": 0,
      "index": 8,
      "width": 1440,
      "height": 379,
      "label": "Figure"
    }
  ]
}